Survivor_Discrete/Survivor_Discrete.py
Survivor_Discrete/__init__.py
binary_survivor-1.0.0.dist-info/METADATA
binary_survivor-1.0.0.dist-info/WHEEL
binary_survivor-1.0.0.dist-info/entry_points.txt
binary_survivor-1.0.0.dist-info/top_level.txt
binary_survivor-1.0.0.dist-info/RECORD
