Metadata-Version: 2.4
Name: binary-survivor
Version: 1.0.0
Summary: A binary optimization algorithm based on survivor-inspired metaheuristics
Author: ُShirmohammad Tavangari
Author-email: shmt.researcher@gmail.com
Keywords: optimization,binary,metaheuristic,evolutionary-algorithm
Classifier: Development Status :: 4 - Beta
Classifier: Intended Audience :: Science/Research
Classifier: License :: OSI Approved :: MIT License
Classifier: Operating System :: OS Independent
Classifier: Programming Language :: Python :: 3
Classifier: Programming Language :: Python :: 3.7
Classifier: Programming Language :: Python :: 3.8
Classifier: Programming Language :: Python :: 3.9
Classifier: Programming Language :: Python :: 3.10
Classifier: Topic :: Scientific/Engineering :: Mathematics
Requires-Python: >=3.7
Requires-Dist: numpy>=1.18.0
Requires-Dist: python>=3.7
Dynamic: author
Dynamic: author-email
Dynamic: classifier
Dynamic: description
Dynamic: description-content-type
Dynamic: keywords
Dynamic: requires-dist
Dynamic: requires-python
Dynamic: summary
